{
    "format_version": "1.18.3",
    "minecraft:client_entity": {
        "description": {
            "identifier": "cobblemon:0924_tandemaus",
            "materials": {
                "default": "entity_emissive_alpha"
            },
            "textures": {
                "default": "textures/entity/0924_tandemaus/tandemaus.png",
                "shiny_default": "textures/entity/0924_tandemaus/shiny_tandemaus.png"
            },
            "animations": {
                "ground_idle": "animation.tandemaus.ground_idle",
                "air_idle": "animation.tandemaus.ground_idle",
                "water_idle": "animation.tandemaus.ground_idle",
                "walking": "animation.tandemaus.walking",
                "controller": "controller.animation.pokemon"
            },
            "render_controllers": [
                {
                    "controller.render.pokemon": "query.property('cobblemon:shiny') ? 1 : 0"
                }
            ],
            "spawn_egg": {
                "texture": "tandemaus",
                "texture_index": 0
            },
            "geometry": {
                "default": "geometry.tandemaus"
            }
        }
    }
}